setup.py
skylink/__init__.py
skylink/ext/__init__.py
skylink/ext/db/__init__.py
skylink/ext/db/main.py
skylink/ext/eredis/__init__.py
skylink/ext/es/__init__.py
skylink/ext/es/main.py
skylink/ext/utils/__init__.py
skylink/ext/utils/db_utils.py
skylink/ext/utils/file_utils.py
skylink/ext/utils/reflect_utils.py
skylink/ext/utils/resp_utils.py
testext.egg-info/PKG-INFO
testext.egg-info/SOURCES.txt
testext.egg-info/dependency_links.txt
testext.egg-info/requires.txt
testext.egg-info/top_level.txt