Metadata-Version: 1.0
Name: testext
Version: 1.0.1.3
Summary: ext sdk
Home-page: UNKNOWN
Author: skyeye
Author-email: skyeye@gmail.com
License: MIT Licence
Keywords: test,ext
Platform: any
